{
  "db_name": "PostgreSQL",
  "query": "SELECT count(*) FROM http_monitors WHERE organization_id = $1 AND status IN ( SELECT unnest($2::integer[])) AND ($3 = '' or url ilike $3 )",
  "describe": {
    "columns": [
      {
        "ordinal": 0,
        "name": "count",
        "type_info": "Int8"
      }
    ],
    "parameters": {
      "Left": [
        "Uuid",
        "Int4Array",
        "Text"
      ]
    },
    "nullable": [
      null
    ]
  },
  "hash": "afcb643c6bed9c18cbfca54f310be13b422d648881fd2ef483d9d52eb7ad19ef"
}
